keras_ernie/__init__.py
keras_ernie/loader.py
keras_ernie/paddle_to_tensor.py
keras_ernie/finetune/__init__.py
keras_ernie/finetune/classifier.py
keras_ernie/finetune/mrc.py
keras_ernie/finetune/sequence_label.py
keras_ernie/model/__init__.py
keras_ernie/model/ernie.py
keras_ernie/model/ernie_v1.py
keras_ernie/model/transformer_encoder.py
keras_ernie/utils/__init__.py
keras_ernie/utils/args.py
keras_ernie/utils/cards.py
keras_ernie/utils/cmrc2018_eval.py
keras_ernie/utils/data.py
keras_ernie/utils/fp16.py
keras_ernie/utils/init.py
keras_ernie-1.0.1.dist-info/METADATA
keras_ernie-1.0.1.dist-info/WHEEL
keras_ernie-1.0.1.dist-info/top_level.txt
keras_ernie-1.0.1.dist-info/RECORD
