Metadata-Version: 2.1
Name: keras-ernie
Version: 1.0.1
Summary: Keras ERNIE
Home-page: https://github.com/LongmaoTeamTf/keras_ernie
Author: WangYao
Author-email: wangyao.sr@gmail.com
License: MIT
Platform: UNKNOWN
Classifier: Programming Language :: Python :: 3
Classifier: License :: OSI Approved :: MIT License
Classifier: Operating System :: OS Independent
Requires-Dist: numpy (==1.16.4)
Requires-Dist: joblib (==0.13.2)
Requires-Dist: paddlepaddle-gpu (==1.6.3.post107)
Requires-Dist: tensorflow-gpu (>=2.0.0)
Requires-Dist: keras-bert (==0.80.0)
